toksum/__init__.py
toksum/cli.py
toksum/core.py
toksum/exceptions.py
toksum-1.1.0.dist-info/licenses/LICENSE
toksum-1.1.0.dist-info/METADATA
toksum-1.1.0.dist-info/WHEEL
toksum-1.1.0.dist-info/entry_points.txt
toksum-1.1.0.dist-info/top_level.txt
toksum-1.1.0.dist-info/RECORD
