Metadata-Version: 2.4
Name: toksum
Version: 1.1.0
Summary: A comprehensive Python library for counting tokens across 300+ LLM models from 32+ providers including OpenAI, Anthropic, Google, Meta, Mistral, and more
Author-email: Raja CSP Raman <raja.csp@gmail.com>
License: MIT
Project-URL: Homepage, https://github.com/kactlabs/toksum
Project-URL: Repository, https://github.com/kactlabs/toksum
Project-URL: Issues, https://github.com/kactlabs/toksum/issues
Keywords: tokens,llm,openai,anthropic,gpt,claude,tokenizer
Classifier: Development Status :: 5 - Production/Stable
Classifier: Intended Audience :: Developers
Classifier: License :: OSI Approved :: MIT License
Classifier: Operating System :: OS Independent
Classifier: Programming Language :: Python :: 3
Classifier: Programming Language :: Python :: 3.8
Classifier: Programming Language :: Python :: 3.9
Classifier: Programming Language :: Python :: 3.10
Classifier: Programming Language :: Python :: 3.11
Classifier: Programming Language :: Python :: 3.12
Classifier: Topic :: Software Development :: Libraries :: Python Modules
Classifier: Topic :: Text Processing :: Linguistic
Requires-Python: >=3.8
License-File: LICENSE
Requires-Dist: tiktoken>=0.5.0
Requires-Dist: anthropic>=0.7.0
Provides-Extra: dev
Requires-Dist: pytest>=7.0.0; extra == "dev"
Requires-Dist: pytest-cov>=4.0.0; extra == "dev"
Requires-Dist: black>=22.0.0; extra == "dev"
Requires-Dist: flake8>=5.0.0; extra == "dev"
Requires-Dist: mypy>=1.0.0; extra == "dev"
Dynamic: license-file
